README.rst
setup.py
ext_pylib/__init__.py
ext_pylib.egg-info/PKG-INFO
ext_pylib.egg-info/SOURCES.txt
ext_pylib.egg-info/dependency_links.txt
ext_pylib.egg-info/requires.txt
ext_pylib.egg-info/top_level.txt
ext_pylib/domain/__init__.py
ext_pylib/domain/domain.py
ext_pylib/files/__init__.py
ext_pylib/files/dir.py
ext_pylib/files/file.py
ext_pylib/files/node.py
ext_pylib/input/__init__.py
ext_pylib/input/prompts.py
ext_pylib/meta/__init__.py
ext_pylib/meta/meta.py
ext_pylib/password/__init__.py
ext_pylib/password/password.py
ext_pylib/terminal/__init__.py
ext_pylib/terminal/ansi.py
ext_pylib/terminal/colors.py
ext_pylib/terminal/interactive_test.py
ext_pylib/user/__init__.py
ext_pylib/user/user.py