Metadata-Version: 1.1
Name: ext-pylib
Version: 0.1
Summary: Extra python libraries for scaffolding server scripts.
Home-page: https://github.com/hbradleyiii/ext_pylib
Author: Harold Bradley III
Author-email: harold@bradleystudio.net
License: MIT License
Download-URL: https://github.com/hbradleyiii/ext_pylib/archive/0.1.tar.gz
Keywords: server development,files,domain names
Platform: UNKNOWN
Classifier: Development Status :: 3 - Alpha
Classifier: Intended Audience :: Developers
Classifier: Topic :: Software Development :: Build Tools
Classifier: License :: OSI Approved :: MIT License
Classifier: Programming Language :: Python :: 2
Classifier: Programming Language :: Python :: 2.6
Classifier: Programming Language :: Python :: 2.7
Classifier: Programming Language :: Python :: 3
Classifier: Programming Language :: Python :: 3.2
Classifier: Programming Language :: Python :: 3.3
Classifier: Programming Language :: Python :: 3.4
Classifier: Programming Language :: Python :: 3.5
